nvgr/__init__.py
nvgr/course.py
nvgr/distance.py
nvgr/format.py
nvgr/latitude.py
nvgr/longitude.py
nvgr/loxodrome.py
nvgr/position.py
nvgr-0.1.6.dist-info/WHEEL
nvgr-0.1.6.dist-info/METADATA
nvgr-0.1.6.dist-info/licenses/LICENSE
nvgr-0.1.6.dist-info/RECORD
