Metadata-Version: 2.1
Name: nvgr
Version: 0.1.6
Summary: Navigare - Nautical calculations
License: GPL-3.0
Author-email: Cees van de Griend <cees@griend.eu>
Requires-Python: >=3.9
Classifier: Development Status :: 3 - Alpha
Classifier: License :: OSI Approved :: GNU General Public License v3 (GPLv3)
Classifier: Operating System :: OS Independent
Classifier: Programming Language :: Python
Classifier: Programming Language :: Python :: 3.10
Classifier: Programming Language :: Python :: 3.11
Classifier: Programming Language :: Python :: 3.9
Project-URL: Documentation, https://nvgr.readthedocs.io/
Project-URL: Source, https://github.com/ceesvandegriend/nvgr
